openhands_cli/__init__.py
openhands_cli/entrypoint.py
openhands_cli/gui_launcher.py
openhands_cli/locations.py
openhands_cli/setup.py
openhands_cli/terminal_compat.py
openhands_cli/theme.py
openhands_cli/utils.py
openhands_cli/version_check.py
openhands_cli/acp_impl/README.md
openhands_cli/acp_impl/__init__.py
openhands_cli/acp_impl/confirmation.py
openhands_cli/acp_impl/main.py
openhands_cli/acp_impl/runner.py
openhands_cli/acp_impl/slash_commands.py
openhands_cli/acp_impl/test_utils.py
openhands_cli/acp_impl/agent/__init__.py
openhands_cli/acp_impl/agent/base_agent.py
openhands_cli/acp_impl/agent/launcher.py
openhands_cli/acp_impl/agent/local_agent.py
openhands_cli/acp_impl/agent/remote_agent.py
openhands_cli/acp_impl/agent/util.py
openhands_cli/acp_impl/events/event.py
openhands_cli/acp_impl/events/shared_event_handler.py
openhands_cli/acp_impl/events/token_streamer.py
openhands_cli/acp_impl/events/tool_state.py
openhands_cli/acp_impl/events/utils.py
openhands_cli/acp_impl/utils/__init__.py
openhands_cli/acp_impl/utils/convert.py
openhands_cli/acp_impl/utils/mcp.py
openhands_cli/acp_impl/utils/resources.py
openhands_cli/argparsers/acp_parser.py
openhands_cli/argparsers/auth_parser.py
openhands_cli/argparsers/cloud_parser.py
openhands_cli/argparsers/main_parser.py
openhands_cli/argparsers/mcp_parser.py
openhands_cli/argparsers/serve_parser.py
openhands_cli/argparsers/util.py
openhands_cli/argparsers/view_parser.py
openhands_cli/argparsers/web_parser.py
openhands_cli/auth/api_client.py
openhands_cli/auth/device_flow.py
openhands_cli/auth/http_client.py
openhands_cli/auth/login_command.py
openhands_cli/auth/logout_command.py
openhands_cli/auth/token_storage.py
openhands_cli/auth/utils.py
openhands_cli/cloud/command.py
openhands_cli/cloud/conversation.py
openhands_cli/conversations/display.py
openhands_cli/conversations/models.py
openhands_cli/conversations/protocols.py
openhands_cli/conversations/viewer.py
openhands_cli/conversations/store/cloud.py
openhands-1.11.0.dist-info/METADATA
openhands-1.11.0.dist-info/WHEEL
openhands-1.11.0.dist-info/entry_points.txt
openhands-1.11.0.dist-info/licenses/LICENSE
openhands-1.11.0.dist-info/RECORD
