Metadata-Version: 2.4
Name: openhands
Version: 1.11.0
Summary: OpenHands CLI - Terminal User Interface for OpenHands AI Agent
Author-email: OpenHands Team <contact@all-hands.dev>
License: MIT
License-File: LICENSE
Classifier: Programming Language :: Python :: 3 :: Only
Classifier: Programming Language :: Python :: 3.12
Classifier: Programming Language :: Python :: 3.13
Requires-Python: ==3.12.*
Requires-Dist: agent-client-protocol<0.8.0,>=0.7.0
Requires-Dist: httpx>=0.25.0
Requires-Dist: openhands-sdk==1.10.0
Requires-Dist: openhands-tools==1.10.0
Requires-Dist: openhands-workspace==1.9.0
Requires-Dist: prompt-toolkit>=3
Requires-Dist: pydantic>=2.7
Requires-Dist: pyperclip>=1.9.0
Requires-Dist: rich<14.3.0
Requires-Dist: streamingjson>=0.0.2
Requires-Dist: textual-autocomplete>=4.0.6
Requires-Dist: textual-serve>=1.1.3
Requires-Dist: textual>=0.79.0
Requires-Dist: typer>=0.17.4
